commit_linter/__init__.py
commit_linter/main.py
commit_linter/hooks/commit-msg
commit_linter/hooks/pre-receive
commit_linter-1.0.3.dist-info/LICENSE
commit_linter-1.0.3.dist-info/METADATA
commit_linter-1.0.3.dist-info/WHEEL
commit_linter-1.0.3.dist-info/entry_points.txt
commit_linter-1.0.3.dist-info/top_level.txt
commit_linter-1.0.3.dist-info/RECORD
