Metadata-Version: 2.1
Name: commit-linter
Version: 1.0.3
Summary: simple git hooks scripts for a better git experience that enforces you to use the known commit messages conventions
Home-page: https://github.com/Hoopher/commit-linter
Author: Hoopher
Author-email: Unknown@no-email.com
License: MIT
Classifier: Programming Language :: Python :: 3
Classifier: License :: OSI Approved :: MIT License
Classifier: Operating System :: OS Independent
Requires-Python: >=3.6
License-File: LICENSE
